pushit/__init__.py
pushit/pushit.py
pushit-0.1.dist-info/DESCRIPTION.rst
pushit-0.1.dist-info/METADATA
pushit-0.1.dist-info/RECORD
pushit-0.1.dist-info/WHEEL
pushit-0.1.dist-info/metadata.json
pushit-0.1.dist-info/top_level.txt
