Metadata-Version: 2.0
Name: pushit
Version: 0.1
Summary: Push notifications sender for ios and android
Home-page: https://github.com/dotpot/pushit
Author: Lukas Šalkauskas
Author-email: halfas.online@gmail.com
License: MIT
Keywords: push notifications apple ios android google cloud messaging
Platform: UNKNOWN
Requires-Dist: pytest
Requires-Dist: pytest-mock
Requires-Dist: ujson
